lektor_css_min.py
lektor_css_min-0.1.1.dist-info/DESCRIPTION.rst
lektor_css_min-0.1.1.dist-info/METADATA
lektor_css_min-0.1.1.dist-info/RECORD
lektor_css_min-0.1.1.dist-info/WHEEL
lektor_css_min-0.1.1.dist-info/entry_points.txt
lektor_css_min-0.1.1.dist-info/metadata.json
lektor_css_min-0.1.1.dist-info/top_level.txt
