Metadata-Version: 2.0
Name: lektor-css-min
Version: 0.1.1
Summary: UNKNOWN
Home-page: https://github.com/joyhchen/lektor-css-min
Author: Joy Chen
Author-email: joyhzchen@gmail.com
License: MIT
Platform: UNKNOWN
Requires-Dist: chardet
Requires-Dist: csscompressor
